{
  "date": "2026-07-17",
  "session": "midday",
  "generated_at": "2026-07-17T06:15:51.669834",
  "global_score": 0.035,
  "india_score": -1.0,
  "overall_score": -0.431,
  "mood": "risk_off",
  "drivers": [
    "Micron has turned into \u2018the most important stock in the market.\u2019 So is it time to worry?",
    "Netflix is getting stingier about its viewing data, and Wall Street isn\u2019t happy",
    "10 U.S. metro areas where builders are slashing prices on new homes",
    "Palo Alto Networks\u2019 stock has been on a tear \u2014 and it could go even higher, according to these bulls",
    "As SpaceX\u2019s stock notches first close below IPO price, the company is gearing up for a crucial launch",
    "Americans say they need $1.2 million to retire. Most are too deep in debt to get there.",
    "GE boosts profit outlook, but stock falls as booming order growth cools",
    "\u2018It\u2019s heartbreaking\u2019: My brother claimed Social Security at 70. He died from cancer after one payment. Why wait to claim?"
  ],
  "global_cues": {
    "dow": {
      "last": 52552.97,
      "chg_pct": -0.2
    },
    "nasdaq": {
      "last": 25881.95,
      "chg_pct": -1.47
    },
    "sp500": {
      "last": 7533.77,
      "chg_pct": -0.51
    },
    "nikkei": {
      "last": 63749.83,
      "chg_pct": -4.62
    },
    "crude": {
      "last": 78.95,
      "chg_pct": -0.82
    },
    "usdinr": {
      "last": 96.36,
      "chg_pct": -0.14
    },
    "gold": {
      "last": 3985.6,
      "chg_pct": -1.44
    }
  },
  "summary": "Overall macro mood is risk-off (-0.43). US Dow -0.2% overnight. Crude -0.8%. USD/INR -0.1%. Notable: Geopolitical conflict / war; Tariffs / trade war.",
  "playbook": [
    "Geopolitical shocks trigger global risk-off; gold up, equities down initially.",
    "Trade-war headlines spook global markets; IT & export names react most."
  ],
  "playbook_bias": "risk_off",
  "article_count": 60
}