{
  "date": "2026-07-01",
  "session": "afternoon",
  "nifty": {
    "symbol": "^NSEI",
    "value": 23865.75,
    "day_change_pct": -0.34,
    "trend_5d": "sideways",
    "trend_20d": "up",
    "ath_pct_60d": -2.52
  },
  "vix": {
    "value": 13.6,
    "level": "normal",
    "percentile_30d": 23.0,
    "avg_30d": 15.4
  },
  "bank_nifty": {
    "symbol": "^NSEBANK",
    "value": 57542.9,
    "day_change_pct": -0.32,
    "trend_5d": "sideways",
    "trend_20d": "strong_up",
    "ath_pct_60d": -1.98,
    "diverging": false
  },
  "sectors": {
    "IT": {
      "symbol": "ITBEES.NS",
      "value": 29.2,
      "day_change_pct": -2.73,
      "trend_5d": "strong_down",
      "trend_20d": "strong_down",
      "ath_pct_60d": -15.73
    },
    "Pharma": {
      "symbol": "PHARMABEES.NS",
      "value": 26.04,
      "day_change_pct": 0.54,
      "trend_5d": "up",
      "trend_20d": "strong_up",
      "ath_pct_60d": -3.2
    },
    "Bank": {
      "symbol": "BANKBEES.NS",
      "value": 596.37,
      "day_change_pct": -0.27,
      "trend_5d": "down",
      "trend_20d": "strong_up",
      "ath_pct_60d": -5.02
    },
    "Infra": {
      "symbol": "INFRABEES.NS",
      "value": 969.18,
      "day_change_pct": -0.2,
      "trend_5d": "down",
      "trend_20d": "up",
      "ath_pct_60d": -2.59
    }
  },
  "market_mood": "neutral",
  "trade_allowed": true,
  "warnings": [],
  "leading_sectors": [
    "Pharma"
  ],
  "market_regime": "normal",
  "sector_breadth": 0.25,
  "lagging_sectors": [
    "IT",
    "Bank",
    "Infra"
  ],
  "intraday_regime": "mixed",
  "macro": {
    "date": "2026-07-01",
    "session": "midday",
    "generated_at": "2026-07-01T07:55:02.979793",
    "global_score": 0.097,
    "india_score": 0.0,
    "overall_score": 0.053,
    "mood": "neutral",
    "drivers": [
      "Your aging parent has a new romance. Here\u2019s how to protect your inheritance \u2014 without looking greedy.",
      "This threat to the chip rally has surged to its highest level since 2015",
      "Bitcoin ETFs were supposed to make selloffs less painful. That theory is being put to the test.",
      "Nike earnings crushed Wall Street\u2019s estimates \u2014 but here\u2019s the catch",
      "\u2018She is retired\u2019: Do I dip into my 401(k) to pay my mother\u2019s $30,000 credit-card debt?",
      "Trump discloses expanding financial empire, including Apple stock, celebration coins and crypto",
      "If LeBron James goes to the Warriors, that team\u2019s roster will be stacked with some of the most expensive players in NBA history",
      "Investors piled into ETFs at a record pace in the first half of 2026. Here\u2019s where their money is flowing."
    ],
    "global_cues": {
      "dow": {
        "last": 52319.2,
        "chg_pct": 0.26
      },
      "nasdaq": {
        "last": 26213.72,
        "chg_pct": 1.52
      },
      "sp500": {
        "last": 7499.36,
        "chg_pct": 0.79
      },
      "nikkei": {
        "last": 70474.96,
        "chg_pct": 0.59
      },
      "crude": {
        "last": 69.5,
        "chg_pct": -1.77
      },
      "usdinr": {
        "last": 94.94,
        "chg_pct": 0.16
      },
      "gold": {
        "last": 4022.9,
        "chg_pct": 0.01
      }
    },
    "summary": "Overall macro mood is neutral (+0.05). US Dow +0.3% overnight. Crude -1.8%. USD/INR +0.2%. Notable: Geopolitical conflict / war; Tariffs / trade war.",
    "playbook": [
      "Geopolitical shocks trigger global risk-off; gold up, equities down initially.",
      "Trade-war headlines spook global markets; IT & export names react most."
    ],
    "playbook_bias": "risk_off",
    "article_count": 60
  },
  "macro_risk_factor": 1.0,
  "fii_dii": {
    "date": "2026-07-01",
    "fii_net_cr": -2556.75,
    "dii_net_cr": 6842.34,
    "combined_net_cr": 4285.59,
    "signal": "strong_inflow",
    "ok": true,
    "error": "",
    "history": [
      {
        "date": "2026-06-23",
        "fii": -635.91,
        "dii": 1035.72,
        "combined": 399.81
      },
      {
        "date": "2026-06-24",
        "fii": 17.86,
        "dii": 680.21,
        "combined": 698.07
      },
      {
        "date": "2026-06-25",
        "fii": -1843.4,
        "dii": 3637.26,
        "combined": 1793.86
      },
      {
        "date": "2026-06-26",
        "fii": 383.76,
        "dii": 5747.75,
        "combined": 6131.51
      },
      {
        "date": "2026-06-29",
        "fii": -1350.1,
        "dii": 2801.45,
        "combined": 1451.35
      },
      {
        "date": "2026-06-30",
        "fii": -1350.1,
        "dii": 2801.45,
        "combined": 1451.35
      },
      {
        "date": "2026-07-01",
        "fii": -2556.75,
        "dii": 6842.34,
        "combined": 4285.59
      }
    ]
  },
  "flow_tailwind": true,
  "pcr": {
    "date": "2026-07-01",
    "pcr": 0.824,
    "reading": "neutral",
    "total_pe_oi": 2681977,
    "total_ce_oi": 3255733,
    "spot": 23865.75,
    "max_pain": 23900.0,
    "max_pain_dist_pct": -0.14,
    "oi_bias": "call_heavy_resistance",
    "ok": true,
    "error": ""
  },
  "oi_note": "Heavy call OI above spot \u2014 option writers see a lid (bearish lean)"
}